azureml/__init__.py
azureml/metrics/NOTICE
azureml/metrics/__init__.py
azureml/metrics/_score.py
azureml/metrics/_scoring_utilities.py
azureml/metrics/_version.py
azureml/metrics/constants.py
azureml/metrics/common/__init__.py
azureml/metrics/common/_logging_utils.py
azureml/metrics/common/_metric_base.py
azureml/metrics/common/_run_utils.py
azureml/metrics/common/_score_utils.py
azureml/metrics/common/_scoring.py
azureml/metrics/common/_scoring_confidence.py
azureml/metrics/common/_validation.py
azureml/metrics/common/azureml_custom_prompt_metric.py
azureml/metrics/common/azureml_metrics.py
azureml/metrics/common/contract.py
azureml/metrics/common/exceptions.py
azureml/metrics/common/import_utilities.py
azureml/metrics/common/reference_codes.py
azureml/metrics/common/scoring.py
azureml/metrics/common/utilities.py
azureml/metrics/common/llm_connector/__init__.py
azureml/metrics/common/llm_connector/_llm.py
azureml/metrics/common/llm_connector/_llm_url_connector.py
azureml/metrics/common/llm_connector/_openai_connector.py
azureml/metrics/common/llm_connector/async_utils.py
azureml/metrics/common/llm_connector/auth_manager.py
azureml/metrics/common/llm_connector/http_connection_utils.py
azureml/metrics/common/llm_connector/llm_utils.py
azureml/metrics/common/templates/__init__.py
azureml/metrics/common/templates/prompt_crafter.py
azureml/metrics/common/templates/prompt_template.py
azureml/metrics/rai/__init__.py
azureml/metrics/rai/_utils.py
azureml/metrics/rai/groundedness/__init__.py
azureml/metrics/rai/groundedness/_groundedness_base.py
azureml/metrics/rai/groundedness/_groundedness_conversation.py
azureml/metrics/rai/groundedness/_groundedness_qa.py
azureml/metrics/rai/groundedness/_llm_groundedness_qa.py
azureml/metrics/tabular/__init__.py
azureml/metrics/tabular/forecasting/__init__.py
azureml/metrics/tabular/forecasting/_forecasting.py
azureml/metrics/tabular/forecasting/azureml_forecasting_metrics.py
azureml/metrics/tabular/regression/__init__.py
azureml_metrics-47.0.0.dist-info/LICENSE.txt
azureml_metrics-47.0.0.dist-info/METADATA
azureml_metrics-47.0.0.dist-info/WHEEL
azureml_metrics-47.0.0.dist-info/top_level.txt
azureml_metrics-47.0.0.dist-info/RECORD
